SROMPy/__init__.py
SROMPy/optimize/Gradient.py
SROMPy/optimize/ObjectiveFunction.py
SROMPy/optimize/Optimizer.py
SROMPy/optimize/__init__.py
SROMPy/postprocess/Postprocessor.py
SROMPy/postprocess/__init__.py
SROMPy/srom/FiniteDifference.py
SROMPy/srom/SROM.py
SROMPy/srom/SROMSurrogate.py
SROMPy/srom/__init__.py
SROMPy/target/AnalyticRandomVector.py
SROMPy/target/BetaRandomVariable.py
SROMPy/target/DiscreteRandomVector.py
SROMPy/target/GammaRandomVariable.py
SROMPy/target/NormalRandomVariable.py
SROMPy/target/RandomEntity.py
SROMPy/target/RandomVariable.py
SROMPy/target/RandomVector.py
SROMPy/target/SampleRandomVector.py
SROMPy/target/UniformRandomVariable.py
SROMPy/target/__init__.py
SROMPy-0.1.0.dist-info/LICENSE
SROMPy-0.1.0.dist-info/METADATA
SROMPy-0.1.0.dist-info/WHEEL
SROMPy-0.1.0.dist-info/top_level.txt
SROMPy-0.1.0.dist-info/RECORD
