Metadata-Version: 2.1
Name: SROMPy
Version: 0.1.0
Summary: Stochastic Reduced Order Models with Python
Home-page: https://github.com/NASA/SROMPy
Author: James Warner 
Author-email: james.e.warner@nasa.gov
License: UNKNOWN
Platform: UNKNOWN
Classifier: Programming Language :: Python :: 2.7
Classifier: License :: OSI Approved :: Apache Software License
Classifier: Operating System :: OS Independent
Requires-Dist: numpy
Requires-Dist: scipy
Requires-Dist: matplotlib
